dynamic_url/__init__.py
dynamic_url/functions.py
dynamic_url/url.py
getDynamicUrl-0.1.1.dist-info/LICENCE.txt
getDynamicUrl-0.1.1.dist-info/METADATA
getDynamicUrl-0.1.1.dist-info/WHEEL
getDynamicUrl-0.1.1.dist-info/top_level.txt
getDynamicUrl-0.1.1.dist-info/RECORD
