Metadata-Version: 2.1
Name: getDynamicUrl
Version: 0.1.1
Summary: Get dyanmic Url
Home-page: UNKNOWN
Author: Jhone Mendez
Author-email: jhone0901@gmail.com
License: MIT
Keywords: dynamicUrl
Platform: UNKNOWN
Classifier: Intended Audience :: Developers
Classifier: Development Status :: 5 - Production/Stable
Classifier: License :: OSI Approved :: MIT License
Classifier: Programming Language :: Python
Classifier: Programming Language :: Python :: 3
Classifier: Programming Language :: Python :: 3.6
Classifier: Programming Language :: Python :: 3.7
Classifier: Programming Language :: Python :: 3.8
Classifier: Programming Language :: Python :: 3.9
Classifier: Operating System :: OS Independent
Requires-Dist: google-cloud-bigquery
Requires-Dist: pyarrow
